PythonQianyiXuexiShiyongZhinanChuyiFix1/README.md
PythonQianyiXuexiShiyongZhinanChuyiFix1/__init__.py
PythonQianyiXuexiShiyongZhinanChuyiFix1/__main__.py
PythonQianyiXuexiShiyongZhinanChuyiFix1/file.epub
PythonQianyiXuexiShiyongZhinanChuyiFix1/index.html
PythonQianyiXuexiShiyongZhinanChuyiFix1/css/__init__.py
PythonQianyiXuexiShiyongZhinanChuyiFix1/css/annotations.css
PythonQianyiXuexiShiyongZhinanChuyiFix1/css/main.css
PythonQianyiXuexiShiyongZhinanChuyiFix1/css/normalize.css
PythonQianyiXuexiShiyongZhinanChuyiFix1/css/popup.css
PythonQianyiXuexiShiyongZhinanChuyiFix1/font/__init__.py
PythonQianyiXuexiShiyongZhinanChuyiFix1/font/fontello.eot
PythonQianyiXuexiShiyongZhinanChuyiFix1/font/fontello.svg
PythonQianyiXuexiShiyongZhinanChuyiFix1/font/fontello.ttf
PythonQianyiXuexiShiyongZhinanChuyiFix1/font/fontello.woff
PythonQianyiXuexiShiyongZhinanChuyiFix1/img/__init__.py
PythonQianyiXuexiShiyongZhinanChuyiFix1/img/annotator-glyph-sprite.png
PythonQianyiXuexiShiyongZhinanChuyiFix1/img/annotator-icon-sprite.png
PythonQianyiXuexiShiyongZhinanChuyiFix1/img/apple-touch-icon.png
PythonQianyiXuexiShiyongZhinanChuyiFix1/img/cancelfullscreen.png
PythonQianyiXuexiShiyongZhinanChuyiFix1/img/close.png
PythonQianyiXuexiShiyongZhinanChuyiFix1/img/fullscreen.png
PythonQianyiXuexiShiyongZhinanChuyiFix1/img/loader.gif
PythonQianyiXuexiShiyongZhinanChuyiFix1/img/menu-icon.png
PythonQianyiXuexiShiyongZhinanChuyiFix1/img/save.png
PythonQianyiXuexiShiyongZhinanChuyiFix1/img/saved.png
PythonQianyiXuexiShiyongZhinanChuyiFix1/img/settings-s.png
PythonQianyiXuexiShiyongZhinanChuyiFix1/img/settings.png
PythonQianyiXuexiShiyongZhinanChuyiFix1/img/star.png
PythonQianyiXuexiShiyongZhinanChuyiFix1/js/__init__.py
PythonQianyiXuexiShiyongZhinanChuyiFix1/js/epub.js
PythonQianyiXuexiShiyongZhinanChuyiFix1/js/epub.min.js
PythonQianyiXuexiShiyongZhinanChuyiFix1/js/epub.min.map
PythonQianyiXuexiShiyongZhinanChuyiFix1/js/hooks.min.js
PythonQianyiXuexiShiyongZhinanChuyiFix1/js/hooks.min.map
python_qianyi_xuexi_shiyong_zhinan_chuyi_fix1-2025.3.24.1.dist-info/METADATA
python_qianyi_xuexi_shiyong_zhinan_chuyi_fix1-2025.3.24.1.dist-info/WHEEL
python_qianyi_xuexi_shiyong_zhinan_chuyi_fix1-2025.3.24.1.dist-info/entry_points.txt
python_qianyi_xuexi_shiyong_zhinan_chuyi_fix1-2025.3.24.1.dist-info/top_level.txt
python_qianyi_xuexi_shiyong_zhinan_chuyi_fix1-2025.3.24.1.dist-info/RECORD
